TCLR/TCLRalgorithm.py
TCLR/__init__.py
TCLR-2.0.4.dist-info/METADATA
TCLR-2.0.4.dist-info/WHEEL
TCLR-2.0.4.dist-info/top_level.txt
TCLR-2.0.4.dist-info/RECORD
