Metadata-Version: 2.1
Name: TCLR
Version: 2.0.4
Summary: Tree-Classifier for Linear Regression (TCLR) is a novel tree model to capture the functional relationships between features and a target based on correlation.
Home-page: https://github.com/Bin-Cao/TCLRmodel
Author: CaoBin
Author-email: bcao@shu.edu.com
Maintainer: CaoBin
Maintainer-email: binjacobcao@gmail.com
License: MIT License
Classifier: Development Status :: 3 - Alpha
Classifier: Intended Audience :: Developers
Classifier: Topic :: Software Development :: Build Tools
Classifier: License :: OSI Approved :: MIT License
Classifier: Programming Language :: Python :: 3
Requires-Python: >=3.7
Requires-Dist: graphviz
Requires-Dist: scipy
Requires-Dist: minepy
Requires-Dist: gplearn
